{"name":"a_registerAccount","id":"com.aspire.testscases.RegistrationTest:a_registerAccount","testCaseName":"com.aspire.testscases.RegistrationTest","userStory":{"id":"com.aspire.testscases.RegistrationTest","storyName":"Registration test","storyClassName":"com.aspire.testscases.RegistrationTest","path":"com.aspire.testscases","type":"story"},"featureTag":{"name":"Testscases/Registration test","type":"story","displayName":"Testscases/Registration test"},"title":"A register account","tags":[{"name":"Testscases/Registration test","type":"story","displayName":"Testscases/Registration test"}],"startTime":"2021-03-15T01:35:00.766987+07:00[Asia/Ho_Chi_Minh]","duration":14391,"projectKey":"","sessionId":"2843c64c8ff4769837cbbfddaaa34db6","driver":"chrome","isManualTestingUpToDate":false,"manual":false,"testSource":"JUnit","order":0,"result":"SUCCESS"}